runai_model_streamer/libstreamer/lib/libstreamergcs.so
runai_model_streamer_gcs/__init__.py
runai_model_streamer_gcs/credentials/__init__.py
runai_model_streamer_gcs/credentials/credentials.py
runai_model_streamer_gcs/files/__init__.py
runai_model_streamer_gcs/files/files.py
runai_model_streamer_gcs/files/tests/__init__.py
runai_model_streamer_gcs/files/tests/test_files.py
runai_model_streamer_gcs-0.15.5.dist-info/LICENSE
runai_model_streamer_gcs-0.15.5.dist-info/METADATA
runai_model_streamer_gcs-0.15.5.dist-info/WHEEL
runai_model_streamer_gcs-0.15.5.dist-info/top_level.txt
runai_model_streamer_gcs-0.15.5.dist-info/RECORD
