Metadata-Version: 2.1
Name: runai-model-streamer-gcs
Version: 0.15.5
Summary: UNKNOWN
Home-page: UNKNOWN
Author: UNKNOWN
Author-email: UNKNOWN
License: UNKNOWN
Platform: UNKNOWN
Requires-Dist: google-auth
Requires-Dist: google-cloud-storage
